README.rst
flask_soy.py
setup.py
Flask_Soy.egg-info/PKG-INFO
Flask_Soy.egg-info/SOURCES.txt
Flask_Soy.egg-info/dependency_links.txt
Flask_Soy.egg-info/not-zip-safe
Flask_Soy.egg-info/requires.txt
Flask_Soy.egg-info/top_level.txt