Metadata-Version: 1.1
Name: Flask-Soy
Version: 0.3
Summary: Provides support for Closure Templates (Soy) in Flask.
Home-page: https://bitbucket.org/lalinsky/flask-soy
Author: Lukas Lalinsky
Author-email: lukas@oxygene.sk
License: Apache
Platform: any
Classifier: Development Status :: 3 - Alpha
Classifier: Environment :: Web Environment
Classifier: Intended Audience :: Developers
Classifier: License :: OSI Approved :: Apache Software License
Classifier: Operating System :: OS Independent
Classifier: Programming Language :: Python
Classifier: Topic :: Internet :: WWW/HTTP :: Dynamic Content
Classifier: Topic :: Software Development :: Libraries :: Python Modules
